cattopy/__init__.py
cattopy/__init__.pyi
cattopy/main.py
catto.py-0.0.4.dist-info/LICENSE
catto.py-0.0.4.dist-info/METADATA
catto.py-0.0.4.dist-info/WHEEL
catto.py-0.0.4.dist-info/top_level.txt
catto.py-0.0.4.dist-info/RECORD
