Metadata-Version: 2.1
Name: catto.py
Version: 0.0.4
Summary: A Python library for making webservers.
Home-page: https://github.com/BoryaGames/catto.py
Author: topcatto
Author-email: feedbackborya@yandex.ru
Keywords: catto cattojs cattopy webserver web server
Classifier: Programming Language :: Python :: 3.12
Classifier: License :: OSI Approved :: MIT License
Classifier: Operating System :: OS Independent
Requires-Python: >=3.7
License-File: LICENSE
Requires-Dist: uvicorn ==0.30.3
